janus/__init__.py
janus/cli.py
janus/set_socrates_env.py
janus/socrates.py
janus/data/comparison_data/Goldblatt13_data.txt
janus/data/comparison_data/Hamano15_data.txt
janus/data/comparison_data/Kopparapu13_data.txt
janus/data/comparison_data/Selsis23_convective.txt
janus/data/luminosity_tracks/luminosity_tracks.pdf
janus/data/tests/config_instellation.toml
janus/data/tests/config_janus.toml
janus/data/tests/config_runaway.toml
janus/modules/__init__.py
janus/modules/compute_moist_adiabat.py
janus/modules/dry_adiabat_setup.py
janus/modules/dry_adiabat_timestep.py
janus/modules/dry_adjustment.py
janus/modules/find_tropopause.py
janus/modules/make_inversion.py
janus/modules/moist_adjustment_H2O.py
janus/modules/plot_emission_spectrum.py
janus/modules/plot_flux_balance.py
janus/modules/relative_humidity.py
janus/modules/set_stratosphere.py
janus/modules/simple_boundary.py
janus/modules/solve_pt.py
janus/modules/spectral_planck_surface.py
janus/modules/water_cloud.py
janus/utils/ClimateGraphicsMPL.py
janus/utils/ClimateUtilities.py
janus/utils/GGRadConv.py
janus/utils/GeneralAdiabat.py
janus/utils/GreyHeat.py
janus/utils/RayleighSpectrum.py
janus/utils/ReadSpectralFile.py
janus/utils/StellarSpectrum.py
janus/utils/__init__.py
janus/utils/atmosphere_column.py
janus/utils/cp_funcs.py
janus/utils/data.py
janus/utils/find_lcl.py
janus/utils/height.py
janus/utils/logs.py
janus/utils/nctools.py
janus/utils/observed_rho.py
janus/utils/phys.py
janus/utils/planets.py
janus/utils/socrates.py
janus/utils/water_tables.py
fwl_janus-24.11.5.dist-info/LICENSE.md
fwl_janus-24.11.5.dist-info/METADATA
fwl_janus-24.11.5.dist-info/WHEEL
fwl_janus-24.11.5.dist-info/entry_points.txt
fwl_janus-24.11.5.dist-info/top_level.txt
fwl_janus-24.11.5.dist-info/RECORD
