Metadata-Version: 2.1
Name: fwl-janus
Version: 24.11.5
Summary: Temperature structure generator for planetory atmospheres.
Author-email: Tim Lichtenberg <tim.lichtenberg@rug.nl>, Mark Hammond <mark.hammond@physics.ox.ac.uk>, Ryan Boukrouche <ryan.boukrouche@astro.su.se>, RJ Graham <arejaygraham@uchicago.edu>, Harrison Nicholls <harrison.nicholls@physics.ox.ac.uk>, Hamish Innes <hamish.innes@physics.ox.ac.uk>, Laurent Soucasse <l.soucasse@esciencecenter.nl>
License: Apache 2.0 License
Project-URL: homepage, https://github.com/FormingWorlds/JANUS
Keywords: exoplanet,atmosphere
Classifier: Intended Audience :: Science/Research
Classifier: License :: OSI Approved :: Apache Software License
Classifier: Operating System :: MacOS :: MacOS X
Classifier: Operating System :: POSIX :: Linux
Classifier: Programming Language :: Python :: 3
Requires-Python: >=3.10
License-File: LICENSE.md
Requires-Dist: click
Requires-Dist: matplotlib
Requires-Dist: natsort
Requires-Dist: netcdf4
Requires-Dist: numpy
Requires-Dist: osfclient
Requires-Dist: pandas
Requires-Dist: platformdirs
Requires-Dist: requests
Requires-Dist: scipy
Requires-Dist: seaborn
Requires-Dist: toml
Requires-Dist: tomlkit
Requires-Dist: f90nml
Provides-Extra: develop
Requires-Dist: bump-my-version; extra == "develop"
Requires-Dist: coverage[toml]; extra == "develop"
Requires-Dist: fwl-mors; extra == "develop"
Requires-Dist: pytest; extra == "develop"
Provides-Extra: docs
Requires-Dist: markdown-include; extra == "docs"
Requires-Dist: mkdocs; extra == "docs"
Requires-Dist: mkdocs-material; extra == "docs"
Requires-Dist: mkdocstrings[python]; extra == "docs"
Provides-Extra: publishing
Requires-Dist: twine; extra == "publishing"
Requires-Dist: wheel; extra == "publishing"
Requires-Dist: build; extra == "publishing"
